{
    "mdx_path": "Mdx\\\u90aa\u6076\u7684\u63a0\u593a\u8005.mdx", 
    "mdx_sounds": [
        "sound/Units/Orc/Wolfrider//RaiderDeath.wav"
    ], 
    "mdx_textures": [
        "units/Demon/ChaosWolfrider/ChaosWolfrider", 
        "Textures/gutz", 
        "Textures/Dust3x"
    ], 
    "meshes": {
        "__tuple__": true, 
        "items": []
    }, 
    "model_id": 134223844, 
    "name": "Mdx\\\u90aa\u6076\u7684\u63a0\u593a\u8005", 
    "physics_meshes": [
        "custom_editor_model/mdx/AutoPhy_\u90aa\u6076\u7684\u63a0\u593a\u8005.mdx"
    ], 
    "pickbound": {
        "__tuple__": true, 
        "items": [
            0.4852638840675354, 
            1.7021311521530151
        ]
    }
}