{
 "f": [
  {
   "__tuple__": true, 
   "items": [
    "", 
    0, 
    2147483647, 
    "code_explorer_custom_root_folder_name"
   ]
  }, 
  {
   "__tuple__": true, 
   "items": [
    "/2147483647", 
    0, 
    "aF0m8ZdcEe+YZ2V7SmaHYI", 
    "\u6d4b\u8bd5\u7528\u9053\u5177"
   ]
  }
 ], 
 "d": {
  "134244374": {
   "__tuple__": true, 
   "items": [
    "aF0m8ZdcEe+YZ2V7SmaHYI", 
    0
   ]
  }, 
  "134254575": {
   "__tuple__": true, 
   "items": [
    "aF0m8ZdcEe+YZ2V7SmaHYI", 
    1
   ]
  }, 
  "134243163": {
   "__tuple__": true, 
   "items": [
    "aF0m8ZdcEe+YZ2V7SmaHYI", 
    2
   ]
  }, 
  "134263503": {
   "__tuple__": true, 
   "items": [
    "aF0m8ZdcEe+YZ2V7SmaHYI", 
    3
   ]
  }, 
  "134257112": {
   "__tuple__": true, 
   "items": [
    "aF0m8ZdcEe+YZ2V7SmaHYI", 
    4
   ]
  }, 
  "134266585": {
   "__tuple__": true, 
   "items": [
    "aF0m8ZdcEe+YZ2V7SmaHYI", 
    5
   ]
  }, 
  "134249462": {
   "__tuple__": true, 
   "items": [
    2147483647, 
    1
   ]
  }, 
  "134232542": {
   "__tuple__": true, 
   "items": [
    2147483647, 
    2
   ]
  }, 
  "134224801": {
   "__tuple__": true, 
   "items": [
    2147483647, 
    3
   ]
  }, 
  "134247449": {
   "__tuple__": true, 
   "items": [
    2147483647, 
    4
   ]
  }, 
  "134231237": {
   "__tuple__": true, 
   "items": [
    2147483647, 
    5
   ]
  }, 
  "134247138": {
   "__tuple__": true, 
   "items": [
    2147483647, 
    6
   ]
  }, 
  "134230698": {
   "__tuple__": true, 
   "items": [
    2147483647, 
    7
   ]
  }, 
  "134231695": {
   "__tuple__": true, 
   "items": [
    2147483647, 
    8
   ]
  }, 
  "134261421": {
   "__tuple__": true, 
   "items": [
    2147483647, 
    9
   ]
  }, 
  "134252249": {
   "__tuple__": true, 
   "items": [
    2147483647, 
    10
   ]
  }, 
  "134277964": {
   "__tuple__": true, 
   "items": [
    2147483647, 
    11
   ]
  }, 
  "134246436": {
   "__tuple__": true, 
   "items": [
    2147483647, 
    12
   ]
  }, 
  "134224703": {
   "__tuple__": true, 
   "items": [
    2147483647, 
    13
   ]
  }, 
  "134243146": {
   "__tuple__": true, 
   "items": [
    2147483647, 
    14
   ]
  }, 
  "134227335": {
   "__tuple__": true, 
   "items": [
    2147483647, 
    15
   ]
  }, 
  "134247588": {
   "__tuple__": true, 
   "items": [
    2147483647, 
    16
   ]
  }, 
  "134264035": {
   "__tuple__": true, 
   "items": [
    2147483647, 
    17
   ]
  }, 
  "134230774": {
   "__tuple__": true, 
   "items": [
    2147483647, 
    18
   ]
  }, 
  "134258102": {
   "__tuple__": true, 
   "items": [
    2147483647, 
    19
   ]
  }, 
  "134241509": {
   "__tuple__": true, 
   "items": [
    2147483647, 
    20
   ]
  }, 
  "134243434": {
   "__tuple__": true, 
   "items": [
    2147483647, 
    21
   ]
  }, 
  "134231108": {
   "__tuple__": true, 
   "items": [
    2147483647, 
    22
   ]
  }, 
  "134254591": {
   "__tuple__": true, 
   "items": [
    2147483647, 
    23
   ]
  }, 
  "134259314": {
   "__tuple__": true, 
   "items": [
    2147483647, 
    24
   ]
  }, 
  "134268907": {
   "__tuple__": true, 
   "items": [
    2147483647, 
    25
   ]
  }, 
  "134266673": {
   "__tuple__": true, 
   "items": [
    2147483647, 
    26
   ]
  }, 
  "134257194": {
   "__tuple__": true, 
   "items": [
    2147483647, 
    27
   ]
  }, 
  "134249675": {
   "__tuple__": true, 
   "items": [
    2147483647, 
    28
   ]
  }, 
  "134238229": {
   "__tuple__": true, 
   "items": [
    2147483647, 
    29
   ]
  }, 
  "134282991": {
   "__tuple__": true, 
   "items": [
    2147483647, 
    30
   ]
  }, 
  "134241214": {
   "__tuple__": true, 
   "items": [
    2147483647, 
    31
   ]
  }, 
  "134262290": {
   "__tuple__": true, 
   "items": [
    2147483647, 
    32
   ]
  }, 
  "134257442": {
   "__tuple__": true, 
   "items": [
    2147483647, 
    33
   ]
  }, 
  "134239693": {
   "__tuple__": true, 
   "items": [
    2147483647, 
    34
   ]
  }, 
  "134241939": {
   "__tuple__": true, 
   "items": [
    2147483647, 
    35
   ]
  }
 }
}